Metadata-Version: 2.1
Name: falguni-102003634
Version: 0.1
Summary: TOPSIS package
Home-page: https://github.com/Falguni7572/falguni_TOPSIS_102003634
Download-URL: https://github.com/Falguni7572/falguni_TOPSIS_102003634/archive/refs/tags/v_01.tar.gz
Author: Falguni Sharma
Author-email: falguni7572@gmail.com
License: MIT
Keywords: TOPSIS,MEANINGFULL,KEYWORDS
Classifier: Development Status :: 3 - Alpha
Classifier: Intended Audience :: Developers
Classifier: Topic :: Software Development :: Build Tools
Classifier: License :: OSI Approved :: MIT License
Classifier: Programming Language :: Python :: 3
Classifier: Programming Language :: Python :: 3.4
Classifier: Programming Language :: Python :: 3.5
Classifier: Programming Language :: Python :: 3.6
License-File: LICENSE.txt
